stdin_to_cloudwatch/__init__.py
stdin_to_cloudwatch/__main__.py
stdin_to_cloudwatch/input_adapters.py
stdin_to_cloudwatch/output_adapters.py
stdin_to_cloudwatch/publish_json_metrics.py
stdin_to_cloudwatch/stream_consumer.py
stdin_to_cloudwatch-0.0.16.dist-info/LICENSE
stdin_to_cloudwatch-0.0.16.dist-info/METADATA
stdin_to_cloudwatch-0.0.16.dist-info/WHEEL
stdin_to_cloudwatch-0.0.16.dist-info/entry_points.txt
stdin_to_cloudwatch-0.0.16.dist-info/top_level.txt
stdin_to_cloudwatch-0.0.16.dist-info/RECORD
