Metadata-Version: 2.1
Name: stdin-to-cloudwatch
Version: 0.0.16
Summary: Intercepts json formatted metrics from process stdin and sends to AWS Cloudwatch
Home-page: https://github.com/jvalduvieco/stdin_to_cloudwatch
Author: Joan Valduvieco
Author-email: jvalduvieco@gmail.com
License: UNKNOWN
Platform: UNKNOWN
Classifier: Programming Language :: Python :: 3
Classifier: License :: OSI Approved :: MIT License
Classifier: Operating System :: OS Independent
Requires-Python: >=3
Requires-Dist: boto3
